json_rm/Attribute.py
json_rm/Entity.py
json_rm/JSONSchema.py
json_rm/__init__.py
json_rm/cli.py
json_rm/formatters/__init__.py
json_rm/formatters/postgres_formatter.py
json_rm/formatters/simple_formatter.py
json_rm/formatters/spark_formatter.py
json_rm-0.0.2.dist-info/LICENSE
json_rm-0.0.2.dist-info/METADATA
json_rm-0.0.2.dist-info/WHEEL
json_rm-0.0.2.dist-info/entry_points.txt
json_rm-0.0.2.dist-info/top_level.txt
json_rm-0.0.2.dist-info/RECORD
