Metadata-Version: 2.1
Name: json-rm
Version: 0.0.2
Summary: Parse JSON Schemas into relational model and transpile into other textual representations.
Author: makes
Project-URL: Homepage, https://github.com/makes/json-rm
Project-URL: Bug Tracker, https://github.com/makes/json-rm/issues
Requires-Python: >=3.9
License-File: LICENSE
Requires-Dist: jsonref
Requires-Dist: typer
